dup_utils/core/__about__.py
dup_utils/core/__init__.py
dup_utils/core/__main__.py
dup_utils/core/cli.py
dup_utils/core/decorator.py
dup_utils/core/dtutils.py
dup_utils/core/parallelize.py
dup_utils/core/pathutils.py
dup_utils/core/randomly.py
dup_utils/core/threader.py
dup_utils/core/base/__init__.py
dup_utils/core/base/cache.py
dup_utils/core/base/checker.py
dup_utils/core/base/convert.py
dup_utils/core/base/elements.py
dup_utils/core/base/filtering.py
dup_utils/core/base/hash.py
dup_utils/core/base/merge.py
dup_utils/core/base/prepare.py
dup_utils/core/base/sorting.py
dup_utils/core/base/splitter.py
dup_utils/core/scripts/__init__.py
dup_utils/core/scripts/git.py
dup_utils/core/scripts/utils.py
dup_utils/core/scripts/version.py
dup_utils/vendor/__init__.py
dup_utils/vendor/dataframe/__init__.py
dup_utils/vendor/dataframe/split.py
dup_utils-0.0.5.post0.dist-info/LICENSE
dup_utils-0.0.5.post0.dist-info/METADATA
dup_utils-0.0.5.post0.dist-info/WHEEL
dup_utils-0.0.5.post0.dist-info/entry_points.txt
dup_utils-0.0.5.post0.dist-info/top_level.txt
dup_utils-0.0.5.post0.dist-info/RECORD
