Metadata-Version: 2.1
Name: dup-utils
Version: 0.0.5.post0
Summary: The utility objects for the data engine package
Author-email: korawica <korawich.anu@gmail.com>
License: MIT
Project-URL: Homepage, https://github.com/korawica/dup_utils/
Project-URL: Source Code, https://github.com/korawica/dup_utils/
Keywords: data,utility
Classifier: Topic :: Utilities
Classifier: Natural Language :: English
Classifier: Development Status :: 3 - Alpha
Classifier: Intended Audience :: Developers
Classifier: Operating System :: OS Independent
Classifier: Programming Language :: Python
Classifier: Programming Language :: Python :: 3 :: Only
Classifier: Programming Language :: Python :: 3.8
Classifier: Programming Language :: Python :: 3.9
Classifier: Programming Language :: Python :: 3.10
Classifier: Programming Language :: Python :: 3.11
Requires-Python: >=3.8.10
License-File: LICENSE
Requires-Dist: ujson <6.0.0,==5.8.0
Requires-Dist: tzdata >=2023.3
Requires-Dist: python-dateutil
Requires-Dist: click >=8.1.3
Requires-Dist: tomli >=2.0.1
Requires-Dist: backports.zoneinfo >=0.2.1 ; python_version == "3.8"
Provides-Extra: dev
Requires-Dist: dup-utils[test] ; extra == 'dev'
Requires-Dist: ruff >=0.0.138 ; extra == 'dev'
Requires-Dist: pre-commit >=3.3.3 ; extra == 'dev'
Requires-Dist: bump2version >=1.0.1 ; extra == 'dev'
Provides-Extra: test
Requires-Dist: pytest >=7.3.2 ; extra == 'test'
Requires-Dist: coverage[toml] >=7.0.0 ; extra == 'test'
Requires-Dist: mypy >=0.982 ; extra == 'test'
Requires-Dist: types-python-dateutil ; extra == 'test'
Requires-Dist: memory-profiler >=0.61.0 ; extra == 'test'
Requires-Dist: perfplot >=0.10.2 ; extra == 'test'
